starfruit/__init__.py
starfruitai-0.0.3.dist-info/LICENSE
starfruitai-0.0.3.dist-info/METADATA
starfruitai-0.0.3.dist-info/WHEEL
starfruitai-0.0.3.dist-info/top_level.txt
starfruitai-0.0.3.dist-info/RECORD
