Metadata-Version: 2.1
Name: starfruitai
Version: 0.0.3
Summary: Starfruit AI - Deep Learning Deployments Made Simple
Home-page: UNKNOWN
Author: Harris Rothaermel
Author-email: harris.rothaermel@gmail.com
License: UNKNOWN
Keywords: python,pytorch,deployment
Platform: UNKNOWN
Classifier: Development Status :: 1 - Planning
Classifier: Intended Audience :: Developers
Classifier: Programming Language :: Python :: 3
Classifier: Operating System :: Unix
Classifier: Operating System :: MacOS :: MacOS X
Classifier: Operating System :: Microsoft :: Windows
Requires-Dist: EasySettings
Requires-Dist: torch
Requires-Dist: requests
